{
	"credit": "Made with Blockbench",
	"texture_size": [18, 77],
	"textures": {
		"0": "thestaff:item/purple_staff",
		"1": "thestaff:item/block",
		"particle": "thestaff:item/purple_staff"
	},
	"elements": [
		{
			"from": [7, 28, 7],
			"to": [9, 30, 9],
			"rotation": {"angle": 0, "axis": "y", "origin": [9, 0, 9]},
			"faces": {
				"north": {"uv": [5.33333, 0, 8.88889, 0.83117], "texture": "#0"},
				"east": {"uv": [5.33333, 0, 8.88889, 0.83117], "texture": "#0"},
				"south": {"uv": [5.33333, 0, 8.88889, 0.83117], "texture": "#0"},
				"west": {"uv": [5.33333, 0.83117, 8.88889, 0], "texture": "#0"},
				"up": {"uv": [5.33333, 16, 8.88889, 15.16883], "texture": "#0"},
				"down": {"uv": [5.33333, 15.16883, 8.88889, 16], "texture": "#0"}
			}
		},
		{
			"from": [7, -6, 7],
			"to": [9, 18, 9],
			"rotation": {"angle": 0, "axis": "y", "origin": [15, 10, 9]},
			"faces": {
				"north": {"uv": [5.33333, 4.98701, 8.88889, 16], "texture": "#0"},
				"east": {"uv": [5.33333, 4.98701, 8.88889, 16], "texture": "#0"},
				"south": {"uv": [5.33333, 4.98701, 8.88889, 16], "texture": "#0"},
				"west": {"uv": [5.33333, 4.98701, 8.88889, 16], "texture": "#0"},
				"up": {"uv": [5.33333, 15.16883, 8.88889, 16], "texture": "#0"},
				"down": {"uv": [5.33333, 15.16883, 8.88889, 16], "texture": "#0"}
			}
		},
		{
			"from": [7, 18, 7],
			"to": [13, 19, 9],
			"rotation": {"angle": 0, "axis": "y", "origin": [17, -12, 9]},
			"faces": {
				"north": {"uv": [5.33333, 4.57143, 16, 4.98701], "texture": "#0"},
				"east": {"uv": [5.33333, 4.57143, 8.88889, 4.98701], "texture": "#0"},
				"south": {"uv": [5.33333, 4.57143, 16, 4.98701], "texture": "#0"},
				"west": {"uv": [5.33333, 14.12987, 8.88889, 14.54545], "texture": "#0"},
				"up": {"uv": [5.33333, 4.98701, 16, 4.57143], "texture": "#0"},
				"down": {"uv": [5.33333, 4.57143, 16, 4.98701], "texture": "#0"}
			}
		},
		{
			"from": [12, 19, 7],
			"to": [13, 27, 9],
			"rotation": {"angle": 0, "axis": "y", "origin": [22, 3, 9]},
			"faces": {
				"north": {"uv": [14.22222, 1.24675, 16, 4.57143], "texture": "#0"},
				"east": {"uv": [5.33333, 4.57143, 8.88889, 4.98701], "texture": "#0"},
				"south": {"uv": [16, 4.57143, 14.22222, 1.24675], "texture": "#0"},
				"west": {"uv": [5.33333, 6.44156, 8.88889, 9.76623], "texture": "#0"},
				"up": {"uv": [5.33333, 4.98701, 16, 4.57143], "texture": "#0"},
				"down": {"uv": [5.33333, 4.57143, 16, 4.98701], "texture": "#0"}
			}
		},
		{
			"from": [7, 27, 7],
			"to": [13, 28, 9],
			"rotation": {"angle": 0, "axis": "y", "origin": [17, -3, 9]},
			"faces": {
				"north": {"uv": [5.33333, 0.83117, 16, 1.24675], "texture": "#0"},
				"east": {"uv": [8.88889, 0.83117, 5.33333, 1.24675], "texture": "#0"},
				"south": {"uv": [16, 1.24675, 5.33333, 0.83117], "texture": "#0"},
				"west": {"uv": [5.33333, 14.33766, 8.88889, 14.75325], "texture": "#0"},
				"up": {"uv": [5.33333, 4.98701, 16, 4.57143], "texture": "#0"},
				"down": {"uv": [5.33333, 4.57143, 16, 4.98701], "texture": "#0"}
			}
		},
		{
			"from": [4, 19, 4],
			"to": [12, 27, 12],
			"rotation": {"angle": 0, "axis": "y", "origin": [4, 19, 4]},
			"faces": {
				"north": {"uv": [0, 0, 16, 16], "texture": "#1"},
				"east": {"uv": [0, 0, 16, 16], "texture": "#1"},
				"south": {"uv": [0, 0, 16, 16], "texture": "#1"},
				"west": {"uv": [0, 0, 16, 16], "texture": "#1"},
				"up": {"uv": [0, 0, 16, 16], "texture": "#1"},
				"down": {"uv": [0, 0, 16, 16], "texture": "#1"}
			}
		}
	],
	"display": {
		"thirdperson_righthand": {
			"translation": [0, 0, 1.5],
			"scale": [0.95, 0.95, 0.95]
		},
		"thirdperson_lefthand": {
			"rotation": [0, 180, 0],
			"translation": [0, 0, 1.5],
			"scale": [0.95, 0.95, 0.95]
		},
		"firstperson_righthand": {
			"rotation": [-30, -79, -36],
			"translation": [7, -6.5, -8.25]
		},
		"firstperson_lefthand": {
			"rotation": [150, 82, -144],
			"translation": [7, -6.5, -8.25]
		},
		"ground": {
			"rotation": [45, -45, 0],
			"translation": [0, 8, 0],
			"scale": [0.9, 0.9, 0.9]
		},
		"gui": {
			"rotation": [-35, -17, -45],
			"translation": [-1.5, -1.5, 0],
			"scale": [0.5, 0.5, 0.5]
		},
		"head": {
			"rotation": [0, 0, 90],
			"translation": [24, 0, 0],
			"scale": [1.6, 1.6, 1.6]
		},
		"fixed": {
			"translation": [0, -2, 0],
			"scale": [0.5, 0.5, 0.5]
		}
	}
}